miqa_offline/__init__.py
miqa_offline/_run_miqa.py
miqa_offline/cli.py
miqa_offline-1.7.2.dist-info/METADATA
miqa_offline-1.7.2.dist-info/WHEEL
miqa_offline-1.7.2.dist-info/entry_points.txt
miqa_offline-1.7.2.dist-info/top_level.txt
miqa_offline-1.7.2.dist-info/RECORD
