Metadata-Version: 2.4
Name: miqa-offline
Version: 1.7.2
Requires-Python: >=3.9
Requires-Dist: requests
Requires-Dist: PyYAML
Requires-Dist: rich
Requires-Dist: miqatools
Requires-Dist: truststore>=0.8
